bapctools/__init__.py
bapctools/__main__.py
bapctools/check_testing_tool.py
bapctools/cli.py
bapctools/config.py
bapctools/conftest.py
bapctools/constraints.py
bapctools/contest.py
bapctools/download_submissions.py
bapctools/export.py
bapctools/fuzz.py
bapctools/generate.py
bapctools/interactive.py
bapctools/latex.py
bapctools/parallel.py
bapctools/problem.py
bapctools/program.py
bapctools/run.py
bapctools/skel.py
bapctools/slack.py
bapctools/solve_stats.py
bapctools/stats.py
bapctools/testcase.py
bapctools/upgrade.py
bapctools/util.py
bapctools/validate.py
bapctools/validator_tests.py
bapctools/verdicts.py
bapctools/visualize.py
bapctools/resources/config/languages.yaml
bapctools/resources/headers/compile_flags.txt
bapctools/resources/headers/validation.h
bapctools/resources/latex/bapc.cls
bapctools/resources/latex/bapcbase.sty
bapctools/resources/latex/contest-problem-slide.tex
bapctools/resources/latex/contest-problem.tex
bapctools/resources/latex/contest-solution.tex
bapctools/resources/latex/contest-web.tex
bapctools/resources/latex/contest.tex
bapctools/resources/latex/contest_data.tex
bapctools/resources/latex/problem-slide.tex
bapctools/resources/latex/problem-slides-base.tex
bapctools/resources/latex/problem-slides.tex
bapctools/resources/latex/problem.tex
bapctools/resources/latex/solution-web.tex
bapctools/resources/latex/solution.tex
bapctools/resources/latex/solutions-base.tex
bapctools/resources/latex/solutions-web.tex
bapctools/resources/latex/solutions.tex
bapctools/resources/latex/images/blank-page-fr.png
bapctools/resources/latex/images/blank-page-fr.tex
bapctools/resources/latex/images/cc-by-sa.pdf
bapctools/resources/latex/images/logo-not-found.pdf
bapctools/resources/latex/lang/da.tex
bapctools/resources/latex/lang/de.tex
bapctools/resources/latex/lang/en.tex
bapctools/resources/latex/lang/es.tex
bapctools/resources/latex/lang/fr.tex
bapctools/resources/latex/lang/is.tex
bapctools/resources/latex/lang/nl.tex
bapctools/resources/skel/.gitignore
bapctools-0.2.dist-info/METADATA
bapctools-0.2.dist-info/WHEEL
bapctools-0.2.dist-info/entry_points.txt
bapctools-0.2.dist-info/licenses/LICENSE
bapctools-0.2.dist-info/RECORD
