Metadata-Version: 2.4
Name: bapctools
Version: 0.2
Summary: Tools for developing ICPC-style programming contest problems.
Project-URL: Homepage, https://github.com/ragnargrootkoerkamp/bapctools
Project-URL: Issues, https://github.com/ragnargrootkoerkamp/bapctools/issues
Author-email: Ragnar Groot Koerkamp <ragnar.grootkoerkamp@gmail.com>
License-Expression: GPL-3.0
License-File: LICENSE
Classifier: Operating System :: OS Independent
Classifier: Programming Language :: Python :: 3
Requires-Python: >=3.10
Requires-Dist: argcomplete~=3.6.3; platform_system != 'Windows'
Requires-Dist: colorama~=0.4.6
Requires-Dist: matplotlib~=3.10.7
Requires-Dist: python-dateutil~=2.9.0
Requires-Dist: questionary~=2.1.1
Requires-Dist: requests~=2.32.5
Requires-Dist: ruamel-yaml~=0.19.1
Provides-Extra: dev
Requires-Dist: mypy~=1.19; extra == 'dev'
Requires-Dist: pre-commit~=4.5.1; extra == 'dev'
Requires-Dist: pytest~=9.0.1; extra == 'dev'
Requires-Dist: types-colorama~=0.4.15; extra == 'dev'
Requires-Dist: types-pygments~=2.18.0; extra == 'dev'
Requires-Dist: types-python-dateutil~=2.9.0; extra == 'dev'
Requires-Dist: types-requests~=2.32.0; extra == 'dev'
Provides-Extra: types
Requires-Dist: mypy~=1.19; extra == 'types'
Requires-Dist: types-colorama~=0.4.15; extra == 'types'
Requires-Dist: types-pygments~=2.18.0; extra == 'types'
Requires-Dist: types-python-dateutil~=2.9.0; extra == 'types'
Requires-Dist: types-requests~=2.32.0; extra == 'types'
